MANIFEST.in
NEWS.txt
README.rst
setup.py
src/hydrat/__init__.py
src/hydrat/cli.py
src/hydrat/configuration.py
src/hydrat/datamodel.py
src/hydrat/experiment.py
src/hydrat/inducer.py
src/hydrat/online.py
src/hydrat/proxy.py
src/hydrat/store.py
src/hydrat/summary.py
src/hydrat.egg-info/PKG-INFO
src/hydrat.egg-info/SOURCES.txt
src/hydrat.egg-info/dependency_links.txt
src/hydrat.egg-info/entry_points.txt
src/hydrat.egg-info/not-zip-safe
src/hydrat.egg-info/requires.txt
src/hydrat.egg-info/top_level.txt
src/hydrat/browser/__init__.py
src/hydrat/browser/browser_config.py
src/hydrat/browser/common.py
src/hydrat/browser/dataset.py
src/hydrat/browser/display.py
src/hydrat/browser/result.py
src/hydrat/browser/spaces.py
src/hydrat/browser/task.py
src/hydrat/classifier/NLTK.py
src/hydrat/classifier/SVM.py
src/hydrat/classifier/WingBaldridge.py
src/hydrat/classifier/__init__.py
src/hydrat/classifier/abstract.py
src/hydrat/classifier/baseline.py
src/hydrat/classifier/common.py
src/hydrat/classifier/flann.py
src/hydrat/classifier/knn.py
src/hydrat/classifier/liblinear.py
src/hydrat/classifier/libsvm.py
src/hydrat/classifier/maxent.py
src/hydrat/classifier/naivebayes.py
src/hydrat/classifier/nearest_prototype.py
src/hydrat/classifier/neuralnet.py
src/hydrat/classifier/nnstrategy.py
src/hydrat/classifier/ordinal.py
src/hydrat/classifier/rainbow.py
src/hydrat/classifier/scikits_learn.py
src/hydrat/classifier/vowpalwabbit.py
src/hydrat/classifier/weka.py
src/hydrat/classifier/meta/__init__.py
src/hydrat/classifier/meta/binary.py
src/hydrat/classifier/meta/featurestacking.py
src/hydrat/classifier/meta/prototype.py
src/hydrat/classifier/meta/repeat.py
src/hydrat/classifier/meta/replicate.py
src/hydrat/classifier/meta/stacking.py
src/hydrat/classifier/meta/stratified.py
src/hydrat/classifier/meta/unknown.py
src/hydrat/classifier/meta/weighted.py
src/hydrat/classifier/sequence/__init__.py
src/hydrat/classifier/sequence/crf.py
src/hydrat/classifier/sequence/markov.py
src/hydrat/classifier/tree/ClassTree.py
src/hydrat/classifier/tree/ClassTreeClassifier.py
src/hydrat/classifier/tree/__init__.py
src/hydrat/common/PorterStemmer.py
src/hydrat/common/__init__.py
src/hydrat/common/bootstrap.py
src/hydrat/common/counter.py
