Metadata-Version: 1.1
Name: hydrat
Version: 0.9.5
Summary: Classifier comparison framework
Home-page: http://hydrat.googlecode.com
Author: Marco Lui
Author-email: saffsd@gmail.com
License: BSD
Keywords: machinelearning textclassification documentprocessing
Platform: UNKNOWN
Classifier: Development Status :: 3 - Alpha
Classifier: Environment :: Console
Classifier: Intended Audience :: Science/Research
Classifier: License :: OSI Approved :: BSD License
Classifier: Operating System :: POSIX :: Linux
Classifier: Programming Language :: Python
Classifier: Topic :: Utilities
